Workbook

Sheet Lire d'abord
A1: Catalogue d'indicateurs PPM — Waterfall / Agile / SAFe
A2: Document de référence pour le cadrage fonctionnel MARCEL. 149 indicateurs.
A4: Ce que ce document n'est pas
A5: Ce n'est pas une maquette de tableau de bord. Un dashboard exploitable comporte 8 à 15 indicateurs par niveau de lecture. Le catalogue sert à choisir, à paramétrer et à documenter, pas à afficher.
A7: Préalables techniques — sans eux, une partie du catalogue n'est pas calculable
A8: 1. Historisation des transitions d'état. Tout indicateur de flux (cycle time, lead time, flow time, flow efficiency, WIP, âge des items, lead time des epics par état du Kanban portefeuille) exige de stocker chaque changement d'état avec son horodatage. Un modèle de données qui ne conserve que l'état courant rend ces indicateurs impossibles à produire a posteriori. C'est une décision de schéma, pas une fonctionnalité d'écran.
A9: 2. Règle de valorisation de l'avancement. L'EVM (CPI, SPI, EV, TCPI) suppose une convention explicite par élément de WBS : 0/100, 50/50, jalons pondérés, ou pourcentage physique sur unités d'œuvre. Sans convention, l'EV est un chiffre déclaratif et tous les indices dérivés sont sans valeur.
A10: 3. Fiabilité de la saisie des temps. En dessous d'environ 90% de taux de saisie dans les délais, tout indicateur de coût interne, de capacité et d'efficience est inexploitable. Cet indicateur (CAP-08) doit être affiché avant ceux qui en dépendent, pas après.
A11: 4. Baselines historisées. Sans conservation des versions de budget et de planning, aucun écart n'est calculable de façon fiable et le rebaseline devient un moyen d'effacer la dérive.
A12: 5. Instrumentation de l'usage. Les indicateurs de bénéfices et d'adoption exigent une mesure prévue avant la mise en service. Rétro-installer une mesure d'adoption après le go-live ne donne jamais de série exploitable.
A14: Agrégation portefeuille multi-méthodes
A15: Un portefeuille mixte waterfall / agile / SAFe n'a pas de dénominateur commun sur la performance d'exécution. La vélocité ne s'additionne pas avec le SPI. Les seules dimensions agrégeables sans perte de sens sont : l'argent (budget, engagé, atterrissage), les dates (jalons, atterrissage), le risque (exposition, criticité), la valeur (bénéfices, adoption) et la fiabilité du reporting. Toute tentative de produire un score de santé unique mélangeant des indicateurs de méthodes différentes produit un chiffre non interprétable.
... A24: La dernière version majeure publiée reste SAFe 6.0 (2023). Scaled Agile a abandonné les releases majeures groupées au profit de mises à jour continues du knowledge base, migré vers framework.scaledagile.com, remplacé les sept core competencies par cinq SAFe Disciplines déclinées en competencies, et retiré les quatre configurations (Essential / Large Solution / Portfolio / Full SAFe) du Big Picture au profit d'un article « Customizing SAFe ». Conséquence directe pour le chantier 9 de MARCEL : positionner le module sur « Full SAFe » reprend une terminologie que l'éditeur a retirée de sa représentation de référence. Les objets (ART, PI, epic, feature, WSJF, PI Objectives) restent inchangés.

Sheet Catalogue
A1: ID | B1: Domaine | C1: Sous-domaine | D1: Indicateur | E1: Méthode | F1: Niveau | G1: Définition | H1: Formule / calcul | I1: Données source requises | J1: Fréquence | K1: Lecture / seuil | L1: Piège / limite | M1: Priorité MARCEL
A2: BUD-01 | B2: Budget & coûts | C2: Cadrage | D2: Budget initial approuvé (BAC) | E2: Transverse | F2: Projet | G2: Montant validé en instance d'engagement, figé comme référence de comparaison. | H2: Saisi (baseline figée) | I2: Décision COPIL/CODIR, fiche projet | J2: À l'engagement + à chaque rebaseline | K2: Doit être immuable ; toute évolution passe par un rebaseline tracé. | L2: Un BAC modifié en douce détruit rétroactivement tous les écarts. Historiser les versions. | M2: P1
A3: BUD-02 | B3: Budget & coûts | C3: Cadrage | D3: Budget révisé | E3: Transverse | F3: Projet | G3: Budget courant après avenants et rebaselines approuvés. | H3: BAC initial + Σ avenants approuvés | I3: Registre des changements | J3: Mensuelle | K3: Écart vs BAC initial = mesure de dérive de cadrage. | L3: Ne jamais fusionner avec le BAC initial dans la même colonne. | M3: P1
A4: BUD-03 | B4: Budget & coûts | C4: Cadrage | D4: Nombre de rebaselines | E4: Transverse | F4: Projet | G4: Compte des re-référencements budget et/ou planning depuis le lancement. | H4: COUNT(versions baseline) | I4: Historique baselines | J4: Mensuelle | K4: >2 sur 12 mois = cadrage instable. | L4: Indicateur politiquement sensible : sert souvent à masquer la dérive plutôt qu'à la traiter. | M4: P2
A5: BUD-04 | B5: Budget & coûts | C5: Exécution | D5: Engagé (commitments) | E5: Transverse | F5: Projet | G5: Montant contractuellement engagé (BC, commandes, contrats) qu'il soit facturé ou non. | H5: Σ commandes émises | I5: ERP achats / SI Finance | J5: Mensuelle | K5: Engagé > budget = alerte immédiate. | L5: Souvent absent des outils PPM : sans interface achats, l'engagé est déclaratif donc faux. | M5: P1
A6: BUD-05 | B6: Budget & coûts | C6: Exécution | D6: Consommé / coût réel (AC) | E6: Transverse | F6: Projet | G6: Coûts réellement constatés à date (facturé + provisions certaines). | H6: Σ factures + provisions | I6: SI Finance, timesheets valorisés | J6: Mensuelle | K6: À comparer à l'avancement physique, jamais au calendrier seul. | L6: Décalage de facturation de 1 à 3 mois : le consommé brut sous-estime toujours la réalité. | M6: P1
A7: BUD-06 | B7: Budget & coûts | C7: Exécution | D7: Reste à engager (RAE) | E7: Transverse | F7: Projet | G7: Part du budget non encore couverte par une commande. | H7: Budget révisé − Engagé | I7: ERP achats | J7: Mensuelle | K7: RAE élevé en fin de projet = risque de report ou de non-consommation. | L7: Confondu avec le reste à faire : ce sont deux choses distinctes. | M7: P2
A8: BUD-07 | B8: Budget & coûts | C8: Prévision | D8: Reste à faire (ETC) | E8: Transverse | F8: Projet | G8: Coût prévisionnel des travaux restants, ré-estimé (pas déduit). | H8: Ré-estimation bottom-up, ou (BAC − EV)/CPI | I8: Fiches projet, CP | J8: Mensuelle | K8: Ré-estimation bottom-up obligatoire au moins trimestriellement. | L8: La formule (BAC−EV)/CPI suppose que la performance passée se reproduit. Faux après changement d'équipe ou de périmètre. | M8: P1
A9: BUD-08 | B9: Budget & coûts | C9: Prévision | D9: Atterrissage (EAC) | E9: Transverse | F9: Projet | G9: Coût total prévisionnel à l'achèvement. | H9: EAC = AC + ETC ; variantes : BAC/CPI ; AC+(BAC−EV)/(CPI×SPI) | I9: AC, EV, ETC | J9: Mensuelle | K9: Publier la méthode retenue à côté du chiffre. | L9: Trois formules donnent trois résultats. Sans méthode affichée, l'EAC est ininterprétable. | M9: P1
A10: BUD-09 | B10: Budget & coûts | C10: Prévision | D10: Écart à l'achèvement (VAC) | E10: Transverse | F10: Projet | G10: Écart prévisionnel entre budget et atterrissage. | H10: VAC = BAC − EAC ; VAC% = VAC/BAC | I10: BAC, EAC | J10: Mensuelle | K10: Seuil RAG usuel : vert <5%, orange 5-10%, rouge >10%. | L10: Le RAG doit porter sur l'atterrissage, pas sur le consommé. | M10: P1
A11: BUD-10 | B11: Budget & coûts | C11: Performance | D11: CPI (indice de performance coût) | E11: Waterfall | F11: Projet | G11: Efficience du coût : valeur acquise par euro dépensé. | H11: CPI = EV / AC | I11: EV, AC | J11: Mensuelle | K11: <0,9 = dérive coût confirmée. | L11: Sans règle de valorisation de l'avancement (0/100, 50/50, % physique), l'EV est déclaratif et le CPI est une fiction. | M11: P1
A12: BUD-11 | B12: Budget & coûts | C12: Performance | D12: CV (écart de coût) | E12: Waterfall | F12: Projet | G12: Écart absolu entre valeur acquise et coût réel. | H12: CV = EV − AC | I12: EV, AC | J12: Mensuelle | K12: Négatif = surcoût à date. | L12: Un CV en valeur absolue n'est pas comparable entre projets de tailles différentes. | M12: P2
... A150: GOU-11 | B150: Gouvernance & reporting | C150: Charge | D150: Charge de production du reporting | E150: Transverse | F150: Portefeuille | G150: Jours-homme consommés par le cycle de reporting mensuel. | H150: Σ jours saisie + consolidation + production | I150: Timesheets PMO | J150: Trimestrielle | K150: À rapporter au nombre de décisions effectivement prises sur la base de ce reporting. | L150: Indicateur que les PMO évitent de produire. C'est pourtant le seul qui justifie l'automatisation. | M150: P2

Sheet Synthèse
A1: Répartition du catalogue
A3: Domaine | B3: P1 | C3: P2 | D3: P3 | E3: Total
A4: Budget & coûts | B4: =COUNTIFS(Catalogue!$B$2:$B$150,$A4,Catalogue!$M$2:$M$150,"P1") -> 16 | C4: =COUNTIFS(Catalogue!$B$2:$B$150,$A4,Catalogue!$M$2:$M$150,"P2") -> 9 | D4: =COUNTIFS(Catalogue!$B$2:$B$150,$A4,Catalogue!$M$2:$M$150,"P3") -> 3 | E4: =SUM(B4:D4) -> 28
A5: Capacité & ressources | B5: =COUNTIFS(Catalogue!$B$2:$B$150,$A5,Catalogue!$M$2:$M$150,"P1") -> 8 | C5: =COUNTIFS(Catalogue!$B$2:$B$150,$A5,Catalogue!$M$2:$M$150,"P2") -> 7 | D5: =COUNTIFS(Catalogue!$B$2:$B$150,$A5,Catalogue!$M$2:$M$150,"P3") -> 2 | E5: =SUM(B5:D5) -> 17
A6: Planning & délais | B6: =COUNTIFS(Catalogue!$B$2:$B$150,$A6,Catalogue!$M$2:$M$150,"P1") -> 9 | C6: =COUNTIFS(Catalogue!$B$2:$B$150,$A6,Catalogue!$M$2:$M$150,"P2") -> 7 | D6: =COUNTIFS(Catalogue!$B$2:$B$150,$A6,Catalogue!$M$2:$M$150,"P3") -> 1 | E6: =SUM(B6:D6) -> 17
A7: Risques & dépendances | B7: =COUNTIFS(Catalogue!$B$2:$B$150,$A7,Catalogue!$M$2:$M$150,"P1") -> 11 | C7: =COUNTIFS(Catalogue!$B$2:$B$150,$A7,Catalogue!$M$2:$M$150,"P2") -> 6 | D7: =COUNTIFS(Catalogue!$B$2:$B$150,$A7,Catalogue!$M$2:$M$150,"P3") -> 0 | E7: =SUM(B7:D7) -> 17
A8: Agile | B8: =COUNTIFS(Catalogue!$B$2:$B$150,$A8,Catalogue!$M$2:$M$150,"P1") -> 9 | C8: =COUNTIFS(Catalogue!$B$2:$B$150,$A8,Catalogue!$M$2:$M$150,"P2") -> 11 | D8: =COUNTIFS(Catalogue!$B$2:$B$150,$A8,Catalogue!$M$2:$M$150,"P3") -> 4 | E8: =SUM(B8:D8) -> 24
A9: SAFe | B9: =COUNTIFS(Catalogue!$B$2:$B$150,$A9,Catalogue!$M$2:$M$150,"P1") -> 12 | C9: =COUNTIFS(Catalogue!$B$2:$B$150,$A9,Catalogue!$M$2:$M$150,"P2") -> 10 | D9: =COUNTIFS(Catalogue!$B$2:$B$150,$A9,Catalogue!$M$2:$M$150,"P3") -> 2 | E9: =SUM(B9:D9) -> 24
A10: Valeur & bénéfices | B10: =COUNTIFS(Catalogue!$B$2:$B$150,$A10,Catalogue!$M$2:$M$150,"P1") -> 4 | C10: =COUNTIFS(Catalogue!$B$2:$B$150,$A10,Catalogue!$M$2:$M$150,"P2") -> 7 | D10: =COUNTIFS(Catalogue!$B$2:$B$150,$A10,Catalogue!$M$2:$M$150,"P3") -> 0 | E10: =SUM(B10:D10) -> 11
A11: Gouvernance & reporting | B11: =COUNTIFS(Catalogue!$B$2:$B$150,$A11,Catalogue!$M$2:$M$150,"P1") -> 8 | C11: =COUNTIFS(Catalogue!$B$2:$B$150,$A11,Catalogue!$M$2:$M$150,"P2") -> 3 | D11: =COUNTIFS(Catalogue!$B$2:$B$150,$A11,Catalogue!$M$2:$M$150,"P3") -> 0 | E11: =SUM(B11:D11) -> 11
A12: Total | B12: =SUM(B4:B11) -> 77 | C12: =SUM(C4:C11) -> 60 | D12: =SUM(D4:D11) -> 12 | E12: =SUM(E4:E11) -> 149
A14: Répartition par méthode
A15: Méthode | B15: Nombre
A16: Transverse | B16: =COUNTIF(Catalogue!$E$2:$E$150,$A16) -> 88
A17: Waterfall | B17: =COUNTIF(Catalogue!$E$2:$E$150,$A17) -> 11
A18: Agile | B18: =COUNTIF(Catalogue!$E$2:$E$150,$A18) -> 23
A19: SAFe | B19: =COUNTIF(Catalogue!$E$2:$E$150,$A19) -> 25
A20: Agile/SAFe | B20: =COUNTIF(Catalogue!$E$2:$E$150,$A20) -> 2
A23: P1 = socle indispensable · P2 = second palier · P3 = optionnel ou dépendant d'un outillage tiers
